aioanticaptcha/__init__.py
aioanticaptcha/antigatetask.py
aioanticaptcha/antinetworking.py
aioanticaptcha/funcaptchaproxyless.py
aioanticaptcha/funcaptchaproxyon.py
aioanticaptcha/geetestproxyless.py
aioanticaptcha/geetestproxyon.py
aioanticaptcha/hcaptchaproxyless.py
aioanticaptcha/hcaptchaproxyon.py
aioanticaptcha/imagecaptcha.py
aioanticaptcha/recaptchav2enterpriseproxyless.py
aioanticaptcha/recaptchav2enterpriseproxyon.py
aioanticaptcha/recaptchav2proxyless.py
aioanticaptcha/recaptchav2proxyon.py
aioanticaptcha/recaptchav3enterpriseproxyless.py
aioanticaptcha/recaptchav3proxyless.py
python3_aioanticaptcha-1.2.dist-info/LICENSE
python3_aioanticaptcha-1.2.dist-info/METADATA
python3_aioanticaptcha-1.2.dist-info/WHEEL
python3_aioanticaptcha-1.2.dist-info/top_level.txt
python3_aioanticaptcha-1.2.dist-info/RECORD
