Metadata-Version: 2.1
Name: python3-aioanticaptcha
Version: 1.2
Summary: Async lib for  Anti-Captcha service.
Home-page: https://github.com/andrersp/aioanticaptcha
Author: André França
Author-email: rsp.assistencia@gmail.com
License: UNKNOWN
Keywords: python,anti-captcha,async
Platform: UNKNOWN
Classifier: Development Status :: 3 - Alpha
Classifier: License :: OSI Approved :: MIT License
Classifier: Programming Language :: Python :: 3.6
Classifier: Programming Language :: Python :: 3.7
Classifier: Programming Language :: Python :: 3.8
Classifier: Programming Language :: Python :: 3.9
Classifier: Programming Language :: Python :: 3.10
Classifier: Operating System :: OS Independent
License-File: LICENSE
Requires-Dist: aiohttp
Requires-Dist: aiofiles
